README.md
setup.py
socket.d.egg-info/PKG-INFO
socket.d.egg-info/SOURCES.txt
socket.d.egg-info/dependency_links.txt
socket.d.egg-info/requires.txt
socket.d.egg-info/top_level.txt
socket.d.egg-info/zip-safe
socketd/SocketD.py
socketd/__init__.py
socketd/broker/BroadcastBroker.py
socketd/broker/BrokerFragmentHandler.py
socketd/broker/BrokerListener.py
socketd/broker/BrokerListenerBase.py
socketd/broker/__init__.py
socketd/cluster/ClusterClient.py
socketd/cluster/ClusterClientSession.py
socketd/cluster/LoadBalancer.py
socketd/cluster/__init__.py
socketd/exception/SocketDExecption.py
socketd/exception/__init__.py
socketd/transport/__init__.py
socketd/transport/client/Client.py
socketd/transport/client/ClientBase.py
socketd/transport/client/ClientChannel.py
socketd/transport/client/ClientConfig.py
socketd/transport/client/ClientConfigHandler.py
socketd/transport/client/ClientConnectHandler.py
socketd/transport/client/ClientConnector.py
socketd/transport/client/ClientConnectorBase.py
socketd/transport/client/ClientHandshakeResult.py
socketd/transport/client/ClientHeartbeatHandler.py
socketd/transport/client/ClientProvider.py
socketd/transport/client/ClientSession.py
socketd/transport/client/__init__.py
socketd/transport/core/Asserts.py
socketd/transport/core/Channel.py
socketd/transport/core/ChannelAssistant.py
socketd/transport/core/ChannelInternal.py
socketd/transport/core/ChannelSupporter.py
socketd/transport/core/Codec.py
socketd/transport/core/Config.py
socketd/transport/core/Costants.py
socketd/transport/core/Entity.py
socketd/transport/core/EntityMetas.py
socketd/transport/core/Flags.py
socketd/transport/core/FragmentAggregator.py
socketd/transport/core/FragmentHandler.py
socketd/transport/core/Frame.py
socketd/transport/core/FrameIoHandler.py
socketd/transport/core/Frames.py
socketd/transport/core/HandshakeDefault.py
socketd/transport/core/IdGenerator.py
socketd/transport/core/Listener.py
socketd/transport/core/Message.py
socketd/transport/core/Processor.py
socketd/transport/core/Session.py
socketd/transport/core/__init__.py
socketd/transport/core/codec/Buffer.py
socketd/transport/core/codec/ByteBufferCodecReader.py
