Metadata-Version: 2.1
Name: socket.d
Version: 2.5.12
Summary: @noear/socket.d python project
Home-page: https://socketd.noear.org/
Author: noear,bai
Classifier: Development Status :: 5 - Production/Stable
Classifier: Intended Audience :: Developers
Classifier: License :: OSI Approved
Classifier: Operating System :: OS Independent
Classifier: Programming Language :: Python
Classifier: Programming Language :: Python :: 3.10
Classifier: Topic :: Software Development :: Libraries
Requires-Python: >=3.10
Requires-Dist: loguru==0.7.2
Requires-Dist: websockets==12.0
